procure/__about__.py
procure/__init__.py
procure/project.py
procure/resource.py
procure/cli/__init__.py
procure/solution/__init__.py
procure/solution/git.py
procure/solution/solution.py
procure/solution/zip.py
procure-0.1.2.dist-info/METADATA
procure-0.1.2.dist-info/WHEEL
procure-0.1.2.dist-info/entry_points.txt
procure-0.1.2.dist-info/licenses/LICENSE
procure-0.1.2.dist-info/RECORD
