Metadata-Version: 2.1
Name: procure
Version: 0.1.2
Summary: Procure build assets
Project-URL: homepage, https://github.com/crungelab/procure
Project-URL: documentation, https://crungelab.github.io/procure/
Project-URL: repository, https://github.com/crungelab/procure
Project-URL: changelog, https://github.com/crungelab/procure/blob/main/CHANGELOG.md
Author-email: Kurtis Fields <kurtisfields@gmail.com>
License: MIT License
License-File: LICENSE
Classifier: Development Status :: 4 - Beta
Classifier: Programming Language :: Python
Classifier: Programming Language :: Python :: 3.8
Classifier: Programming Language :: Python :: 3.9
Classifier: Programming Language :: Python :: 3.10
Classifier: Programming Language :: Python :: 3.11
Classifier: Programming Language :: Python :: Implementation :: CPython
Classifier: Programming Language :: Python :: Implementation :: PyPy
Requires-Python: >=3.8
Requires-Dist: click~=8.1.7
Requires-Dist: requests~=2.31.0
Provides-Extra: dev
Requires-Dist: black~=22.12.0; extra == 'dev'
Provides-Extra: test
Requires-Dist: pytest~=7.2.1; extra == 'test'
